autoprepml/__init__.py
autoprepml/autoeda.py
autoprepml/cleaning.py
autoprepml/cli.py
autoprepml/cli_config.py
autoprepml/config.py
autoprepml/config_manager.py
autoprepml/core.py
autoprepml/dashboard.py
autoprepml/detection.py
autoprepml/feature_engine.py
autoprepml/graph.py
autoprepml/image.py
autoprepml/llm_suggest.py
autoprepml/reports.py
autoprepml/text.py
autoprepml/timeseries.py
autoprepml/utils.py
autoprepml/visualization.py
autoprepml-1.3.0.dist-info/licenses/LICENSE
autoprepml-1.3.0.dist-info/METADATA
autoprepml-1.3.0.dist-info/WHEEL
autoprepml-1.3.0.dist-info/entry_points.txt
autoprepml-1.3.0.dist-info/top_level.txt
autoprepml-1.3.0.dist-info/RECORD
