Metadata-Version: 2.4
Name: autoprepml
Version: 1.3.0
Summary: AI-Assisted Multi-Modal Data Preprocessing Pipeline for ML
Home-page: https://github.com/mdshoaibuddinchanda/autoprepml
Author: MD Shoaibuddin Chanda
Author-email: MD Shoaibuddin Chanda <mdshoaibuddinchanda@gmail.com>
License: MIT
Project-URL: Homepage, https://github.com/mdshoaibuddinchanda/autoprepml
Project-URL: Documentation, https://autoprepml.readthedocs.io
Project-URL: Repository, https://github.com/mdshoaibuddinchanda/autoprepml
Project-URL: Bug Tracker, https://github.com/mdshoaibuddinchanda/autoprepml/issues
Keywords: machine-learning,data-preprocessing,data-cleaning,automl
Classifier: Development Status :: 4 - Beta
Classifier: Intended Audience :: Developers
Classifier: Intended Audience :: Science/Research
Classifier: License :: OSI Approved :: MIT License
Classifier: Programming Language :: Python :: 3
Classifier: Programming Language :: Python :: 3.10
Classifier: Programming Language :: Python :: 3.11
Classifier: Programming Language :: Python :: 3.12
Classifier: Programming Language :: Python :: 3.13
Classifier: Topic :: Scientific/Engineering :: Artificial Intelligence
Classifier: Topic :: Software Development :: Libraries :: Python Modules
Requires-Python: >=3.10
License-File: LICENSE
Requires-Dist: pandas==2.2.2
Requires-Dist: numpy==1.26.4
Requires-Dist: scikit-learn==1.7.2
Requires-Dist: matplotlib==3.10.7
Requires-Dist: seaborn==0.13.2
Requires-Dist: jinja2==3.1.6
Requires-Dist: pyyaml==6.0.3
Requires-Dist: imbalanced-learn==0.12.0
Requires-Dist: Pillow>=10.0.0
Provides-Extra: dev
Requires-Dist: pytest==8.4.2; extra == "dev"
Requires-Dist: pytest-cov==7.0.0; extra == "dev"
Requires-Dist: black==24.10.0; extra == "dev"
Requires-Dist: ruff==0.8.4; extra == "dev"
Provides-Extra: docs
Requires-Dist: mkdocs>=1.4.0; extra == "docs"
Requires-Dist: mkdocs-material>=8.0.0; extra == "docs"
Provides-Extra: llm
Requires-Dist: openai>=1.0.0; extra == "llm"
Requires-Dist: anthropic>=0.18.0; extra == "llm"
Requires-Dist: google-generativeai>=0.3.0; extra == "llm"
Requires-Dist: ollama>=0.1.0; extra == "llm"
Provides-Extra: viz
Requires-Dist: plotly>=5.0.0; extra == "viz"
Requires-Dist: streamlit>=1.0.0; extra == "viz"
Provides-Extra: all
Requires-Dist: pytest==8.4.2; extra == "all"
Requires-Dist: pytest-cov==7.0.0; extra == "all"
Requires-Dist: black==24.10.0; extra == "all"
Requires-Dist: ruff==0.8.4; extra == "all"
Requires-Dist: openai>=1.0.0; extra == "all"
Requires-Dist: anthropic>=0.18.0; extra == "all"
Requires-Dist: google-generativeai>=0.3.0; extra == "all"
Requires-Dist: ollama>=0.1.0; extra == "all"
Requires-Dist: plotly>=5.0.0; extra == "all"
Requires-Dist: streamlit>=1.0.0; extra == "all"
Dynamic: author
Dynamic: home-page
Dynamic: license-file
Dynamic: requires-python
